odoo/addons/hr_attendance_reason/README.rst
odoo/addons/hr_attendance_reason/__init__.py
odoo/addons/hr_attendance_reason/__manifest__.py
odoo/addons/hr_attendance_reason/controllers/__init__.py
odoo/addons/hr_attendance_reason/controllers/main.py
odoo/addons/hr_attendance_reason/demo/hr_attendance_reason_demo.xml
odoo/addons/hr_attendance_reason/i18n/bg.po
odoo/addons/hr_attendance_reason/i18n/de.po
odoo/addons/hr_attendance_reason/i18n/es.po
odoo/addons/hr_attendance_reason/i18n/fr.po
odoo/addons/hr_attendance_reason/i18n/hr_attendance_reason.pot
odoo/addons/hr_attendance_reason/i18n/it.po
odoo/addons/hr_attendance_reason/models/__init__.py
odoo/addons/hr_attendance_reason/models/hr_attendance.py
odoo/addons/hr_attendance_reason/models/hr_attendance_reason.py
odoo/addons/hr_attendance_reason/models/hr_employee.py
odoo/addons/hr_attendance_reason/models/res_company.py
odoo/addons/hr_attendance_reason/models/res_config_settings.py
odoo/addons/hr_attendance_reason/readme/CONTRIBUTORS.md
odoo/addons/hr_attendance_reason/readme/DESCRIPTION.md
odoo/addons/hr_attendance_reason/readme/USAGE.md
odoo/addons/hr_attendance_reason/security/ir.model.access.csv
odoo/addons/hr_attendance_reason/security/security.xml
odoo/addons/hr_attendance_reason/static/description/icon.png
odoo/addons/hr_attendance_reason/static/description/index.html
odoo/addons/hr_attendance_reason/static/src/components/attendance_menu/attendance_menu.esm.js
odoo/addons/hr_attendance_reason/static/src/components/attendance_menu/attendance_menu.xml
odoo/addons/hr_attendance_reason/static/src/components/kiosk_reason/kiosk_reason.esm.js
odoo/addons/hr_attendance_reason/static/src/components/kiosk_reason/kiosk_reason.xml
odoo/addons/hr_attendance_reason/static/src/public_kiosk/public_kiosk_app.esm.js
odoo/addons/hr_attendance_reason/static/src/public_kiosk/public_kiosk_app.xml
odoo/addons/hr_attendance_reason/static/src/scss/hr_attendance_reason.scss
odoo/addons/hr_attendance_reason/tests/__init__.py
odoo_addon_hr_attendance_reason-18.0.1.0.1.dist-info/METADATA
odoo_addon_hr_attendance_reason-18.0.1.0.1.dist-info/WHEEL
odoo_addon_hr_attendance_reason-18.0.1.0.1.dist-info/top_level.txt
odoo_addon_hr_attendance_reason-18.0.1.0.1.dist-info/RECORD
