Metadata-Version: 2.1
Name: odoo-addon-hr_attendance_reason
Version: 18.0.1.0.1
Requires-Python: >=3.10
Requires-Dist: odoo==18.0.*
Summary: HR Attendance Reason
Home-page: https://github.com/OCA/hr-attendance
License: LGPL-3
Author: Odoo S.A., Tecnativa, Odoo Community Association (OCA)
Author-email: support@odoo-community.org
Classifier: Programming Language :: Python
Classifier: Framework :: Odoo
Classifier: Framework :: Odoo :: 18.0
Classifier: License :: OSI Approved :: GNU Lesser General Public License v3 (LGPLv3)
